mcp_vods/__init__.py
mcp_vods/__main__.py
mcp_vods/mitv.py
mcp_vods/moon.py
mcp_vods/tvbox.py
mcp_vods/vods.py
mcp_vods-0.1.9.dist-info/METADATA
mcp_vods-0.1.9.dist-info/WHEEL
mcp_vods-0.1.9.dist-info/entry_points.txt
mcp_vods-0.1.9.dist-info/licenses/LICENSE
mcp_vods-0.1.9.dist-info/RECORD
