Metadata-Version: 2.4
Name: mcp-vods
Version: 0.1.9
Summary: MCP Server for Binge-watch / MoonTV / LunaTV. 一个用于追剧/追番的MCP服务器，为AI提供搜索影视播放地址的能力，并支持在小米等安卓电视/投影仪上直接播放
Project-URL: Repository, https://github.com/aahl/mcp-vods
License: MIT
License-File: LICENSE
Keywords: binge,llm,mcp,media,movie,tv,video
Requires-Python: >=3.10
Requires-Dist: aiohttp>=3.9.0
Requires-Dist: cachetools>=6.2.0
Requires-Dist: fastmcp<3.0.0,>=2.0.0
Requires-Dist: pyyaml>=6.0.0
